CHANGELOG.rst
LICENSE
MANIFEST.in
README.md
README.rst
dev_requirements.txt
opt_requirements.txt
requirements.txt
setup.cfg
setup.py
tox.ini
simiki/__init__.py
simiki/cli.py
simiki/compat.py
simiki/config.py
simiki/generators.py
simiki/initiator.py
simiki/jinja_exts.py
simiki/log.py
simiki/server.py
simiki/updater.py
simiki/utils.py
simiki/watcher.py
simiki.egg-info/PKG-INFO
simiki.egg-info/SOURCES.txt
simiki.egg-info/dependency_links.txt
simiki.egg-info/entry_points.txt
simiki.egg-info/requires.txt
simiki.egg-info/top_level.txt
simiki/conf_templates/Dockerfile
simiki/conf_templates/_config.yml.in
simiki/conf_templates/fabfile.py
simiki/conf_templates/gettingstarted.md
simiki/themes/simple/base.html
simiki/themes/simple/index.html
simiki/themes/simple/page.html
simiki/themes/simple/stat.html
simiki/themes/simple/static/css/style.css
simiki/themes/simple/static/css/tango.css
simiki/themes/simple2/base.html
simiki/themes/simple2/index.html
simiki/themes/simple2/page.html
simiki/themes/simple2/static/css/style.css
simiki/themes/simple2/static/css/tango.css
tests/__init__.py
tests/test_cli.py
tests/test_generators.py
tests/test_initiator.py
tests/test_log.py
tests/test_parse_config.py
tests/test_updater.py
tests/test_utils.py